.
setup.cfg
setup.py
/
Capsule.egg-info/PKG-INFO
Capsule.egg-info/SOURCES.txt
Capsule.egg-info/dependency_links.txt
Capsule.egg-info/requires.txt
Capsule.egg-info/top_level.txt
bin/capsule
capsule/__init__.py
capsule/capsule.py
capsule/container.py
capsule/image.py
capsule.egg-info/SOURCES.txt