Metadata-Version: 1.1
Name: capsule
Version: 0.1.3
Summary: Manage development environments like virtualenv but with docker containers and export your python history to iPythonNotebook
Home-page: https://github.com/tryexceptpass/capsule
Author: Cristian Medina
Author-email: cabkarian@gmail.com
License: MIT
Keywords: docker,virtualenv,environments,ipynb,ipythonnotebook
Platform: UNKNOWN
Classifier: License :: OSI Approved :: MIT License
Classifier: Topic :: Software Development
Classifier: Topic :: Scientific/Engineering
Classifier: Topic :: System
Classifier: Topic :: Software Development :: Testing
Classifier: Topic :: Utilities
Classifier: Development Status :: 4 - Beta
Classifier: Framework :: IPython
